fslparser/__init__.py
fslparser/main.py
fslparser/parsers.py
fslparser-0.0.1.dist-info/LICENSE.txt
fslparser-0.0.1.dist-info/METADATA
fslparser-0.0.1.dist-info/WHEEL
fslparser-0.0.1.dist-info/top_level.txt
fslparser-0.0.1.dist-info/RECORD
