Metadata-Version: 2.1
Name: fslparser
Version: 0.0.1
Summary: fsl-parser
Home-page: UNKNOWN
Author: Fatemeh
Author-email: 
License: UNKNOWN
Platform: UNKNOWN
Classifier: Programming Language :: Python :: 3
Classifier: License :: OSI Approved :: MIT License
Classifier: Operating System :: OS Independent
Requires-Python: >=3.6
